_sortedl1.cp314-win32.pyd
sortedl1/__init__.py
sortedl1/estimators.py
sortedl1/results.py
sortedl1-1.6.0.dist-info/METADATA
sortedl1-1.6.0.dist-info/WHEEL
sortedl1-1.6.0.dist-info/licenses/LICENSE
sortedl1-1.6.0.dist-info/RECORD
