Metadata-Version: 2.1
Name: sortedl1
Version: 1.6.0
Summary: Sorted L-One Penalized Estimation
Keywords: statistics,machine-learning
Author: Quentin Klopfenstein, Malgorzata Bogdan
Author-Email: Johan Larsson <johanlarsson@outlook.com>, Mathurin Massias <mathurin.massias@gmail.com>, Jonas Wallin <jonas.wallin@stat.lu.se>
Maintainer-Email: Johan Larsson <johanlarsson@outlook.com>
License: GNU General Public License
Classifier: Development Status :: 3 - Alpha
Classifier: Intended Audience :: Science/Research
Classifier: Intended Audience :: Developers
Classifier: License :: OSI Approved :: GNU General Public License v3 or later (GPLv3+)
Classifier: Operating System :: MacOS
Classifier: Operating System :: Microsoft :: Windows
Classifier: Operating System :: POSIX :: Linux
Classifier: Operating System :: POSIX
Classifier: Operating System :: Unix
Classifier: Programming Language :: C++
Classifier: Programming Language :: Python :: 3 :: Only
Classifier: Programming Language :: Python :: 3.9
Classifier: Programming Language :: Python :: 3.10
Classifier: Programming Language :: Python :: 3.11
Classifier: Programming Language :: Python :: 3.12
Classifier: Programming Language :: Python :: 3.13
Classifier: Topic :: Scientific/Engineering
Project-URL: homepage, https://github.com/jolars/sortedl1
Project-URL: documentation, https://jolars.github.io/sortedl1/
Project-URL: changelog, https://github.com/jolars/sortedl1/blob/main/CHANGELOG.md
Project-URL: tracker, https://github.com/jolars/sortedl1/issues
Requires-Python: >=3.9
Requires-Dist: numpy>=1.20
Requires-Dist: scikit-learn>=1.0
Requires-Dist: scipy>=0.18.0
Provides-Extra: docs
Requires-Dist: sphinx; extra == "docs"
Requires-Dist: furo; extra == "docs"
Requires-Dist: sphinx-copybutton; extra == "docs"
Requires-Dist: myst-parser; extra == "docs"
Provides-Extra: tests
Requires-Dist: pytest; extra == "tests"
Requires-Dist: sphinx; extra == "tests"
Provides-Extra: plots
Requires-Dist: matplotlib>=3.5.0; extra == "plots"
